labrador_sdk/__init__.py
labrador_sdk/gpio.py
labrador_sdk/main.py
labrador_sdk/pwm.py
tests/__init__.py
tests/test_gpio.py
tests/test_labrador_sdk.py
tests/test_pwm.py
labrador_sdk-0.0.2.dist-info/LICENSE
labrador_sdk-0.0.2.dist-info/METADATA
labrador_sdk-0.0.2.dist-info/WHEEL
labrador_sdk-0.0.2.dist-info/top_level.txt
labrador_sdk-0.0.2.dist-info/RECORD
