Metadata-Version: 2.1
Name: labrador-sdk
Version: 0.0.2
License-File: LICENSE
Requires-Dist: rich
